pretty_plotly/__init__.py
pretty_plotly/plot.py
pretty_plotly-0.0.1.dist-info/LICENSE
pretty_plotly-0.0.1.dist-info/METADATA
pretty_plotly-0.0.1.dist-info/WHEEL
pretty_plotly-0.0.1.dist-info/top_level.txt
pretty_plotly-0.0.1.dist-info/RECORD
