Metadata-Version: 2.2
Name: pretty_plotly
Version: 0.0.1
Summary: Handy functions for easier, simpler plotting with the plotly library.
Author-email: Bheki <bhekimaenetja@gmail.com>
Project-URL: Homepage, https://github.com/bheki-maenetja/pretty-plotly
Classifier: Programming Language :: Python :: 3
Classifier: Operating System :: OS Independent
Classifier: Topic :: Software Development :: Libraries :: Python Modules
Requires-Python: >=3.8
License-File: LICENSE
